ReaderOutputXmlRobotFramework/ReaderRobotFramework.py
ReaderOutputXmlRobotFramework/__init__.py
tests/__init__.py
tests/test_ReaderRobotFramework.py
ReadOutputXml_RobotFramework-0.0.5.1.dist-info/LICENSE
ReadOutputXml_RobotFramework-0.0.5.1.dist-info/METADATA
ReadOutputXml_RobotFramework-0.0.5.1.dist-info/WHEEL
ReadOutputXml_RobotFramework-0.0.5.1.dist-info/top_level.txt
ReadOutputXml_RobotFramework-0.0.5.1.dist-info/RECORD
