Metadata-Version: 2.1
Name: ReadOutputXml-RobotFramework
Version: 0.0.5.1
Summary: Reader the output xml from structure RobotFramework output
Home-page: https://github.com/mcdeva/ReaderOutputXml-RobotFramework.git
Author: Rukpong
Author-email: aisendbox@gmail.com
License: MIT
Platform: UNKNOWN
Classifier: Programming Language :: Python :: 3
Classifier: License :: OSI Approved :: MIT License
Classifier: Development Status :: 3 - Alpha
License-File: LICENSE
Requires-Dist: requests
